Workbook

Sheet Verdict
A1: The Analyst — Business Proposition v0.1 (backward from a Tier-1 salary)
A2: Yan Finance Review (Hasib #30 lead, Harini #45, Priya #9) · council RDS · 2026-06-19
A4: THE QUESTION
A5: Can ONE clean ad per page sustainably fund a Tier-1 analyst salary (LKR 150,000 ≈ US$500/mo)?
A6: (Salary is founder-stated this session: tiers 150k/300k/500k LKR ≈ $500/$1,000/$1,500. Not an invented value.)
A8: HEADLINE VERDICT — [KILLED as stated]
A9: One ad per page CANNOT fund $500/mo in Year 1. To net $500 (grossed for fees/forex/fill ≈ $593),
A10: a single clean ad needs ~300,000–420,000 pageviews/month at realistic blended RPM. A new Sri Lankan
A11: investigative site runs 5k–50k/mo in year one — a 6–17x gap even on the best scenario.
A13: WHAT ACTUALLY WORKS — [ENDORSED]
A14: Membership-led + a clean ad as a thin supplement. At Base traffic (~60k pv/mo): ~150 members at $3/mo
A15: ≈ $450 + ad ~$90 ≈ $540 > target. This is on-ethos (community-funded, Pillar 2) and ad-independent.
... A31: Sheets: Assumptions · Backward Math · Scenarios · Workload · Sources. Edit BLUE cells; YELLOW = verify.

Sheet Assumptions
A1: Assumptions — edit BLUE; verify YELLOW
A3: Target & costs
A4: Tier-1 salary target (USD/mo) | B4: 500 | C4: Founder-stated: LKR 150,000 ≈ $500. [V:FOUNDER]
A5: USD→LKR rate | B5: 305 | C5: ASSUMPTION — verify live rate.
A6: Platform infra (USD/mo) | B6: 16.25 | C6: From Business Model v0.1 (Cloudflare+Supabase free+domain+misc).
A7: Gross-up (fees/forex/fill/viewability) | B7: 0.15 | C7: Ad fill, viewability, ad-block leakage, payout forex/fees.
A8: Gross revenue needed (USD/mo) | B8: =(B4+B6)*(1+B7) -> 593.6875
A10: Ad RPM (one clean ad/page, effective)
A11: Sri Lanka traffic RPM (USD/1000) | B11: 0.5 | C11: SL=AdSense T9 (lowest). News single unit ~$0.30–1.00. Source: AdSense RPM-by-country 2026.
A12: Diaspora (Tier-1) RPM (USD/1000) | B12: 3 | C12: EthicalAds ~$2.50 EU/NA clean ad; Tier-1 news single unit ~$2–5. Sources: EthicalAds; tier CPM 2026.
A13: Membership (on-ethos primary)
A14: Avg membership (USD/member/mo) | B14: 3 | C14: Blended SL + diaspora supporters. Pillar-2 community funding.

Sheet Backward Math
A1: Backward math: pageviews needed for one ad to hit the target
A2: Pageviews needed = gross revenue needed ÷ RPM × 1000. Target links from Assumptions.
A4: Blended RPM (USD/1000) | B4: Pageviews needed / mo | C4: vs new-site reality (≈30k) | D4: Read
A5: 0.5 | B5: =Assumptions!$B$8/A5*1000 -> 1187375 | C5: =B5/30000 -> 39.579167 | D5: pure SL
A6: 1 | B6: =Assumptions!$B$8/A6*1000 -> 593687.5 | C6: =B6/30000 -> 19.789583 | D6: SL/diaspora blend
A7: 1.5 | B7: =Assumptions!$B$8/A7*1000 -> 395791.67 | C7: =B7/30000 -> 13.193056 | D7: SL/diaspora blend
A8: 2 | B8: =Assumptions!$B$8/A8*1000 -> 296843.75 | C8: =B8/30000 -> 9.8947917 | D8: diaspora-heavy / clean premium
A9: 3 | B9: =Assumptions!$B$8/A9*1000 -> 197895.83 | C9: =B9/30000 -> 6.5965278 | D9: diaspora-heavy / clean premium
A11: Reading: even at a diaspora-heavy $2–3 RPM you need ~200k–300k pv/mo; pure-SL needs ~1M+.

Sheet Scenarios
A1: Scenarios — Year-1 steady state (≈month 12)
A2: Pageviews/splits/pieces from Strategic Council (Atsuko/Ridma/Sahani). Treat pv as lumpy midpoints, not floors.
A4: Driver | B4: Lean | C4: Base | D4: Growth | E4: Diaspora-tilt
A5: Monthly pageviews (mo12) | B5: 25000 | C5: 60000 | D5: 130000 | E5: 100000
A6: Sri Lanka traffic share | B6: 0.7 | C6: 0.6 | D6: 0.55 | E6: 0.4
A7: Diaspora share | B7: =1-B6 -> 0.3 | C7: =1-C6 -> 0.4 | D7: =1-D6 -> 0.45 | E7: =1-E6 -> 0.6
A8: Blended RPM (USD/1000) | B8: =B6*Assumptions!$B$11+B7*Assumptions!$B$12 -> 1.25 | C8: =C6*Assumptions!$B$11+C7*Assumptions!$B$12 -> 1.5 | D8: =D6*Assumptions!$B$11+D7*Assumptions!$B$12 -> 1.625 | E8: =E6*Assumptions!$B$11+E7*Assumptions!$B$12 -> 2
A9: Ad revenue (USD/mo) | B9: =B5/1000*B8 -> 31.25 | C9: =C5/1000*C8 -> 90 | D9: =D5/1000*D8 -> 211.25 | E9: =E5/1000*E8 -> 200
A10: Gross revenue needed (USD/mo) | B10: =Assumptions!$B$8 -> 593.6875 | C10: =Assumptions!$B$8 -> 593.6875 | D10: =Assumptions!$B$8 -> 593.6875 | E10: =Assumptions!$B$8 -> 593.6875
A11: Ad-only shortfall (USD/mo) | B11: =B9-B10 -> -562.4375 | C11: =C9-C10 -> -503.6875 | D11: =D9-D10 -> -382.4375 | E11: =E9-E10 -> -393.6875
A12: Pageviews needed for ad-only | B12: =B10/B8*1000 -> 474950 | C12: =C10/C8*1000 -> 395791.67 | D12: =D10/D8*1000 -> 365346.15 | E12: =E10/E8*1000 -> 296843.75
A13: Traffic gap (×) | B13: =B12/B5 -> 18.998 | C13: =C12/C5 -> 6.5965278 | D13: =D12/D5 -> 2.810355 | E13: =E12/E5 -> 2.9684375
A15: HYBRID: members to close the gap (with ad)
A16: Members needed (ad + membership = target) | B16: =MAX(0,ROUNDUP((B10-B9)/Assumptions!$B$14,0)) -> 188 | C16: =MAX(0,ROUNDUP((C10-C9)/Assumptions!$B$14,0)) -> 168 | D16: =MAX(0,ROUNDUP((D10-D9)/Assumptions!$B$14,0)) -> 128 | E16: =MAX(0,ROUNDUP((E10-E9)/Assumptions!$B$14,0)) -> 132
A17: Pieces/month (big+small) | B17: 10 | C17: 13 | D17: 16 | E17: 12
A18: Note: Growth assumes +0.5–1 FTE support (added labour cost, not in this view).

Sheet Workload
A1: Workload reality (Ridma #44 / Sahani #35)
A3: Item | B3: Finding
A4: Proposed cadence | B4: 1 big + 1 small per working day | C4: ≈20 big + 20 small/month
A5: Sustainable solo cadence | B5: ~2–4 big + 8–12 small / month | C5: 3–5x below the proposal
A6: Defensible "big" dossier | B6: 3–10 days each | C6: two-source rule, Alleged Checker, compliance labels
A7: The four jobs in one body | B7: researcher+journalist+marketer+brand | C7: marketing spike collides with publish spike
A8: Breaking point | B8: verification gets cut first | C8: existential legal/credibility risk (the #1 asset)
A9: Scaling fix | B9: stable of branded analysts | C9: centralize legal/verification/SEO/distribution; replicate the person
A10: Binding scaling constraint | B10: verification/legal capacity | C10: NOT article volume

Sheet Sources
A1: Sources & provenance (SD-COMMS-COMPLIANCE-2: cite before numbers leave council)
A3: Claim | B3: Source
A4: Salary target LKR 150k ≈ $500 | B4: Founder-stated this session [V:FOUNDER]
A5: SL = AdSense lowest tier (T9); news RPM low | B5: AdSense RPM by country 2026 (partnerkin / adstimate / worldpopulationreview)
A6: Clean contextual ad ≈ $2.50 CPM (EU/NA) | B6: EthicalAds publisher guide / prospectus 2026
A7: Tier-1 CPM $16–21; Tier-3 <$3; news <$2 RPM | B7: Adsterra / Trafficcardinal tier guides; 15m.com
A8: SL Meta CPM ≈ LKR 173 (~$0.55) | B8: hypesrilanka.com 2026; Statista SL digital advertising
A9: Ad-block heaviest in 18–34 tech cohort | B9: SQ Magazine / Backlinko ad-blocker stats 2026
A10: AdSense ban/invalid-traffic single-point risk | B10: Google AdSense Help (account closure / invalid traffic)
A11: New-site traffic back-loaded, power-law spiky | B11: Animalz; Averi; Neil Patel; GIJN; Nieman Lab
A12: Infra cost basis | B12: Analyst Business Model v0.1 (Cloudflare/Supabase/Resend 2026 pricing)
