Workbook

Sheet README
A1: The Analyst — Business Model v0.1
A2: A Yan service • prepared 2026-06-19 • status: DRAFT for founder review (Riz + Sunera)
A4: PURPOSE
A5: First-pass financial operating model for The Analyst (analyst.rizrazak.com). Closes the gaps named in the
A6: business/financial planning stocktake: no breakeven, no burn/runway/P&L, no funding ledger.
A8: ETHOS LOCK (from docs/strategy.md)
A9: • Funded by cooperative ventures + community support. NO corporate sponsorship. NO programmatic ads.
A10: • Independence is demonstrated, not claimed — revenue must not create an agenda or a patron.
A11: • Transparency: practise what we preach. This model is built to be publishable in a transparency report.
A12: • Reframe the stocktake gap "ad rate-card / media kit" as a SUPPORTER / MEMBERSHIP PROSPECTUS to stay on-ethos.
A14: HOW TO USE
A15: 1. Edit only BLUE cells (inputs). BLACK cells are formulas; GREEN cells link across sheets. Do not overtype them.
... A27: • Will Phase-2 cooperative surplus cross-subsidise journalism, and from when? • Founder stipends: volunteer or paid?

Sheet Assumptions
A1: Assumptions — edit BLUE cells only
A2: Currency base: USD. All monthly costs USD unless noted. Verify YELLOW cells before publishing.
A4: Currency & period
A5: USD → LKR exchange rate | B5: 305 | C5: ASSUMPTION — verify current mid-market rate (placeholder).
A6: Model horizon | B6: Jul 2026 – Jun 2027
A7: Model period = Year 1 (12 months)
A9: Infrastructure — fixed (USD / month)
A10: Cloudflare Workers Paid | B10: 5 | C10: Source: Cloudflare Workers pricing, 2026 — $5/mo base (10M req, 30M CPU-ms).
A11: Supabase (Free=0 / Pro=25) | B11: 0 | C11: Source: Supabase pricing 2026 — Free tier viable now; Pro $25/mo when limits hit.
A12: Resend email (Free=0 / Pro=20) | B12: 0 | C12: Source: Resend pricing 2026 — Free 3,000 emails/mo (100/day); Pro $20/mo.
A13: Domain (amortised /mo) | B13: 1.25 | C13: rizrazak.com at-cost registrar ~$15/yr; GitHub Pages hosting free.
A14: Misc tools / buffer | B14: 10 | C14: Backups, analytics, fonts, small SaaS buffer — adjust to real.
A15: Total infra / month | B15: =SUM(B10:B14) -> 16.25
A17: People — stipends (USD / month)
A18: Editorial stipend (Riz) | B18: 0 | C18: Default 0 = volunteer. Enter target stipend when funded.
A19: Co-founder stipend (Sunera) | B19: 0 | C19: Default 0 = volunteer. Sunera Bandara, co-founder (joined Jun 2026).
A20: Translation / contributor pool | B20: 0 | C20: Sinhala/Tamil contributors, fact-check, per Google-baseline translation policy.
A21: Total people / month | B21: =SUM(B18:B20) -> 0
A23: One-off / annual (USD) — amortised monthly
A24: Legal contingency reserve (annual) | B24: 0 | C24: Defamation/ICCPR risk per strategy.md threat model. Fund when able.
A25: Design / asset pipeline (annual) | B25: 0 | C25: Thumbnails, hero images, brand assets.
A26: One-off amortised / month | B26: =(B24+B25)/12 -> 0
A28: Revenue drivers — ILLUSTRATIVE (replace with real)
A29: Recurring supporters at start (count) | B29: 0 | C29: Members/patrons giving monthly. Placeholder — enter real.
A30: Avg recurring pledge (USD / supporter / mo) | B30: 3 | C30: Blended SL + diaspora. Diaspora skews higher; SL lower.
A31: Recurring supporter growth (% / month) | B31: 0 | C31: Month-over-month net growth. Keep conservative for v0.1.
A32: One-off pledges / donations (USD / mo) | B32: 0 | C32: From pledge-portal funnel (caravan-fresh). Placeholder.
A33: Aligned grants (USD / year) | B33: 0 | C33: Press-freedom/journalism foundations only; no agenda strings. Spread /12.
A34: Cooperative surplus transfer (USD / mo, start) | B34: 0 | C34: Phase-2 ventures cross-subsidising journalism. 0 until ventures live.
A35: Cooperative surplus growth (% / month) | B35: 0 | C35: Once a venture is operating.
A37: Starting position
A38: Opening cash (USD) | B38: 0 | C38: Enter real available runway capital. Placeholder 0.

Sheet Monthly P&L
A1: Monthly P&L & Runway (USD) — Year 1
A2: BLACK = formulas; GREEN = links to Assumptions. All driven by the Assumptions sheet.
A4: Line item (USD) | B4: Jul-26 | C4: Aug-26 | D4: Sep-26 | E4: Oct-26 | F4: Nov-26 | G4: Dec-26 | H4: Jan-27 | I4: Feb-27 | J4: Mar-27 | K4: Apr-27 | L4: May-27 | M4: Jun-27 | N4: Year 1
A5: REVENUE
A6: Recurring supporters (count) | B6: =Assumptions!B29 -> 0 | C6: =B6*(1+Assumptions!$B$31) -> 0 | D6: =C6*(1+Assumptions!$B$31) -> 0 | E6: =D6*(1+Assumptions!$B$31) -> 0 | F6: =E6*(1+Assumptions!$B$31) -> 0 | G6: =F6*(1+Assumptions!$B$31) -> 0 | H6: =G6*(1+Assumptions!$B$31) -> 0 | I6: =H6*(1+Assumptions!$B$31) -> 0 | J6: =I6*(1+Assumptions!$B$31) -> 0 | ... M6: =L6*(1+Assumptions!$B$31) -> 0 | N6: =M6 -> 0
A7: Recurring pledge revenue | B7: =B6*Assumptions!$B$30 -> 0 | C7: =C6*Assumptions!$B$30 -> 0 | D7: =D6*Assumptions!$B$30 -> 0 | E7: =E6*Assumptions!$B$30 -> 0 | F7: =F6*Assumptions!$B$30 -> 0 | G7: =G6*Assumptions!$B$30 -> 0 | H7: =H6*Assumptions!$B$30 -> 0 | I7: =I6*Assumptions!$B$30 -> 0 | ... M7: =M6*Assumptions!$B$30 -> 0 | N7: =SUM(B7:M7) -> 0
A8: One-off pledges / donations | B8: =Assumptions!$B$32 -> 0 | C8: =Assumptions!$B$32 -> 0 | D8: =Assumptions!$B$32 -> 0 | E8: =Assumptions!$B$32 -> 0 | F8: =Assumptions!$B$32 -> 0 | G8: =Assumptions!$B$32 -> 0 | H8: =Assumptions!$B$32 -> 0 | I8: =Assumptions!$B$32 -> 0 | ... M8: =Assumptions!$B$32 -> 0 | N8: =SUM(B8:M8) -> 0
A9: Aligned grants (amortised) | B9: =Assumptions!$B$33/12 -> 0 | C9: =Assumptions!$B$33/12 -> 0 | D9: =Assumptions!$B$33/12 -> 0 | E9: =Assumptions!$B$33/12 -> 0 | F9: =Assumptions!$B$33/12 -> 0 | G9: =Assumptions!$B$33/12 -> 0 | H9: =Assumptions!$B$33/12 -> 0 | I9: =Assumptions!$B$33/12 -> 0 | ... M9: =Assumptions!$B$33/12 -> 0 | N9: =SUM(B9:M9) -> 0
A10: Cooperative surplus transfer | B10: =Assumptions!B34 -> 0 | C10: =B10*(1+Assumptions!$B$35) -> 0 | D10: =C10*(1+Assumptions!$B$35) -> 0 | E10: =D10*(1+Assumptions!$B$35) -> 0 | F10: =E10*(1+Assumptions!$B$35) -> 0 | G10: =F10*(1+Assumptions!$B$35) -> 0 | H10: =G10*(1+Assumptions!$B$35) -> 0 | I10: =H10*(1+Assumptions!$B$35) -> 0 | J10: =I10*(1+Assumptions!$B$35) -> 0 | ... M10: =L10*(1+Assumptions!$B$35) -> 0 | N10: =SUM(B10:M10) -> 0
A11: Total revenue | B11: =SUM(B7:B10) -> 0 | C11: =SUM(C7:C10) -> 0 | D11: =SUM(D7:D10) -> 0 | E11: =SUM(E7:E10) -> 0 | F11: =SUM(F7:F10) -> 0 | G11: =SUM(G7:G10) -> 0 | H11: =SUM(H7:H10) -> 0 | I11: =SUM(I7:I10) -> 0 | ... M11: =SUM(M7:M10) -> 0 | N11: =SUM(B11:M11) -> 0
A13: OPERATING COSTS
A14: Cloudflare Workers | B14: =Assumptions!$B$10 -> 5 | C14: =Assumptions!$B$10 -> 5 | D14: =Assumptions!$B$10 -> 5 | E14: =Assumptions!$B$10 -> 5 | F14: =Assumptions!$B$10 -> 5 | G14: =Assumptions!$B$10 -> 5 | H14: =Assumptions!$B$10 -> 5 | I14: =Assumptions!$B$10 -> 5 | ... M14: =Assumptions!$B$10 -> 5 | N14: =SUM(B14:M14) -> 60
A15: Supabase | B15: =Assumptions!$B$11 -> 0 | C15: =Assumptions!$B$11 -> 0 | D15: =Assumptions!$B$11 -> 0 | E15: =Assumptions!$B$11 -> 0 | F15: =Assumptions!$B$11 -> 0 | G15: =Assumptions!$B$11 -> 0 | H15: =Assumptions!$B$11 -> 0 | I15: =Assumptions!$B$11 -> 0 | ... M15: =Assumptions!$B$11 -> 0 | N15: =SUM(B15:M15) -> 0
A16: Resend email | B16: =Assumptions!$B$12 -> 0 | C16: =Assumptions!$B$12 -> 0 | D16: =Assumptions!$B$12 -> 0 | E16: =Assumptions!$B$12 -> 0 | F16: =Assumptions!$B$12 -> 0 | G16: =Assumptions!$B$12 -> 0 | H16: =Assumptions!$B$12 -> 0 | I16: =Assumptions!$B$12 -> 0 | ... M16: =Assumptions!$B$12 -> 0 | N16: =SUM(B16:M16) -> 0
A17: Domain (amortised) | B17: =Assumptions!$B$13 -> 1.25 | C17: =Assumptions!$B$13 -> 1.25 | D17: =Assumptions!$B$13 -> 1.25 | E17: =Assumptions!$B$13 -> 1.25 | F17: =Assumptions!$B$13 -> 1.25 | G17: =Assumptions!$B$13 -> 1.25 | H17: =Assumptions!$B$13 -> 1.25 | I17: =Assumptions!$B$13 -> 1.25 | ... M17: =Assumptions!$B$13 -> 1.25 | N17: =SUM(B17:M17) -> 15
A18: Misc tools / buffer | B18: =Assumptions!$B$14 -> 10 | C18: =Assumptions!$B$14 -> 10 | D18: =Assumptions!$B$14 -> 10 | E18: =Assumptions!$B$14 -> 10 | F18: =Assumptions!$B$14 -> 10 | G18: =Assumptions!$B$14 -> 10 | H18: =Assumptions!$B$14 -> 10 | I18: =Assumptions!$B$14 -> 10 | ... M18: =Assumptions!$B$14 -> 10 | N18: =SUM(B18:M18) -> 120
A19: People / stipends | B19: =Assumptions!$B$21 -> 0 | C19: =Assumptions!$B$21 -> 0 | D19: =Assumptions!$B$21 -> 0 | E19: =Assumptions!$B$21 -> 0 | F19: =Assumptions!$B$21 -> 0 | G19: =Assumptions!$B$21 -> 0 | H19: =Assumptions!$B$21 -> 0 | I19: =Assumptions!$B$21 -> 0 | ... M19: =Assumptions!$B$21 -> 0 | N19: =SUM(B19:M19) -> 0
A20: One-off / annual (amortised) | B20: =Assumptions!$B$26 -> 0 | C20: =Assumptions!$B$26 -> 0 | D20: =Assumptions!$B$26 -> 0 | E20: =Assumptions!$B$26 -> 0 | F20: =Assumptions!$B$26 -> 0 | G20: =Assumptions!$B$26 -> 0 | H20: =Assumptions!$B$26 -> 0 | I20: =Assumptions!$B$26 -> 0 | ... M20: =Assumptions!$B$26 -> 0 | N20: =SUM(B20:M20) -> 0
A21: Total costs | B21: =SUM(B14:B20) -> 16.25 | C21: =SUM(C14:C20) -> 16.25 | D21: =SUM(D14:D20) -> 16.25 | E21: =SUM(E14:E20) -> 16.25 | F21: =SUM(F14:F20) -> 16.25 | G21: =SUM(G14:G20) -> 16.25 | H21: =SUM(H14:H20) -> 16.25 | I21: =SUM(I14:I20) -> 16.25 | ... M21: =SUM(M14:M20) -> 16.25 | N21: =SUM(B21:M21) -> 195
A23: Net surplus / (deficit) | B23: =B11-B21 -> -16.25 | C23: =C11-C21 -> -16.25 | D23: =D11-D21 -> -16.25 | E23: =E11-E21 -> -16.25 | F23: =F11-F21 -> -16.25 | G23: =G11-G21 -> -16.25 | H23: =H11-H21 -> -16.25 | I23: =I11-I21 -> -16.25 | ... M23: =M11-M21 -> -16.25 | N23: =SUM(B23:M23) -> -195
A24: Opening cash | B24: =Assumptions!B38 -> 0 | C24: =B25 -> -16.25 | D24: =C25 -> -32.5 | E24: =D25 -> -48.75 | F24: =E25 -> -65 | G24: =F25 -> -81.25 | H24: =G25 -> -97.5 | I24: =H25 -> -113.75 | J24: =I25 -> -130 | ... M24: =L25 -> -178.75
A25: Closing cash | B25: =B24+B23 -> -16.25 | C25: =C24+C23 -> -32.5 | D25: =D24+D23 -> -48.75 | E25: =E24+E23 -> -65 | F25: =F24+F23 -> -81.25 | G25: =G24+G23 -> -97.5 | H25: =H24+H23 -> -113.75 | I25: =I24+I23 -> -130 | ... M25: =M24+M23 -> -195
A27: Year-1 net surplus / (deficit): | B27: =N23 -> -195
A28: Avg monthly burn if revenue=0 (USD): | B28: =N21/12 -> 16.25
A29: Runway at current opening cash & zero revenue (months): | B29: =IF((N21/12)=0,"n/a",Assumptions!B38/(N21/12)) -> 0

Sheet Breakeven
A1: Breakeven — how much community support covers the platform
A2: Breakeven = total monthly cost ÷ average recurring pledge. Black cells are formulas.
A4: Total fixed cost / month (infra + people + amortised) | B4: =Assumptions!B15+Assumptions!B21+Assumptions!B26 -> 16.25
A5: Average recurring pledge (USD / supporter / mo) | B5: =Assumptions!B30 -> 3
A6: Breakeven supporters needed (recurring only) | B6: =IF(B5=0,"-",ROUNDUP(B4/B5,0)) -> 6
A7: Current recurring supporters | B7: =Assumptions!B29 -> 0
A8: Gap to breakeven (supporters) | B8: =MAX(0,B6-B7) -> 6
A9: Breakeven in LKR / month | B9: =B4*Assumptions!B5 -> 4956.25
A11: Note: at $0 stipends, breakeven is just infra — a few dozen modest supporters. Stipends raise the bar materially.

Sheet Scenarios
A1: Scenarios — Year 1 (USD)
A2: Edit BLUE supporter & pledge inputs per scenario; fixed annual cost links from Assumptions.
A4: Driver | B4: Lean | C4: Base | D4: Growth
A5: Recurring supporters (avg) | B5: 25 | C5: 100 | D5: 400
A6: Avg pledge (USD/mo) | B6: 3 | C6: 3.5 | D6: 4
A7: One-off + grants (USD/yr) | B7: 0 | C7: 600 | D7: 3000
A8: Coop surplus (USD/yr) | B8: 0 | C8: 0 | D8: 1200
A9: Annual revenue (USD) | B9: =B5*B6*12+B7+B8 -> 900 | C9: =C5*C6*12+C7+C8 -> 4800 | D9: =D5*D6*12+D7+D8 -> 23400
A10: Annual fixed cost (USD) | B10: =(Assumptions!$B$15+Assumptions!$B$21+Assumptions!$B$26)*12 -> 195 | C10: =(Assumptions!$B$15+Assumptions!$B$21+Assumptions!$B$26)*12 -> 195 | D10: =(Assumptions!$B$15+Assumptions!$B$21+Assumptions!$B$26)*12 -> 195
A11: Net Year 1 (USD) | B11: =B9-B10 -> 705 | C11: =C9-C10 -> 4605 | D11: =D9-D10 -> 23205

Sheet Funding Ledger
A1: Funding Ledger (starter) — committed vs received
A2: Schema brief for the future database-backed ledger. Every entry must carry a Source ID for traceability.
A4: Date | B4: Source / Supporter | C4: Type | D4: Currency | E4: Amount | F4: Status | G4: Restriction | H4: Notes | I4: Source ID
C5: recurring | one-off | grant | coop-surplus
F6: committed | received
D14: Received total | E14: =SUMIF(F5:F12,"received",E5:E12) -> 0
D15: Committed total | E15: =SUMIF(F5:F12,"committed",E5:E12) -> 0
A17: Schema fields: date, source, type(enum), currency, amount(numeric), status(enum), restriction(text), notes, source_id(FK).
A18: Belongs in the central Yan People/finance store eventually; do NOT build a parallel Analyst-only funding DB without approval.
