Workbook

Sheet Verdict
A1: The Analyst → Media Company — Finance v0.4 (path to $600, cost, scaling)
A2: Hasib #30 (lead), Harini #45 · 2 finance rounds · 2026-06-19 · prudent · diaspora-led
A4: ROUND 1 — fastest credible path to ~$600/mo
A5: Membership is the backbone (diaspora pays, by viewer location). $600 = 120 members @ $5 OR 60 @ $10.
A6: A realistic STACK (current inputs): 80 members @ $5 ($400) + YT long-form ($120) + diaspora display ($210) + Shorts/tips ($65) ≈ $795 — clears $600 with headroom.
A7: Shorts are ACQUISITION, not revenue (Shorts RPM ~$0.10). Their job is to fill the membership funnel from diaspora reach.
A8: Diaspora English traffic is the unlock: YouTube ~$8 RPM (US/UK audience) vs ~$0.70 domestic — a 6–10x multiplier.
A10: ROUND 2 — cost & scaling
A11: Phase-1 burn (3–5 paid-per-piece contributors + shorts tools + infra) ≈ $400–650/mo — roughly the same as the revenue target.
A12: So Phase 1 ≈ breakeven by design: members fund the contributors who make the content that wins the members. Bootstrap loop.
A13: Scaling: per-contributor cost is variable (paid per accepted piece); central overhead/analyst falls as the roster grows.
A14: Binding constraint = verification capacity, not contributor count (Mara/Tech Review).
... A20: Sheets: Assumptions · Revenue to $600 · Diaspora YT/Shorts · Cost & Scaling · Sources. Tax: see v0.3 (Tier-1 ~tax-free).

Sheet Assumptions
A1: Assumptions — edit BLUE; prudent. Diaspora-led.
A3: Target
A4: Revenue target (USD/mo) | B4: 600 | C4: founder: ~$600 fast
A5: Membership (backbone)
A6: Membership price low (USD/mo) | B6: 5 | C6: diaspora supporter
A7: Membership price high (USD/mo) | B7: 10 | C7: committed patron
A8: Assumed paying members | B8: 80 | C8: editable
A9: Visitor→member conversion | B9: 0.005 | C9: prudent 0.3–1%
A10: YouTube / Shorts (diaspora, by viewer location)
A11: YT long-form views/mo | B11: 30000 | C11: diaspora English news
A12: YT long-form RPM (USD/1000) | B12: 4 | C12: English diaspora news; example $8 finance, prudent $4. India domestic $0.70.
A13: Shorts views/mo | B13: 300000 | C13: high-volume acquisition
A14: Shorts RPM (USD/1000) | B14: 0.1 | C14: Shorts pay tiny — acquisition not revenue
A15: Display + tips
A16: Site pageviews/mo (diaspora-tilt) | B16: 120000
A17: Display RPM (USD/1000) | B17: 1.76 | C17: diaspora single clean ad, from v0.2
A18: Tips/donations (USD/mo) | B18: 35 | C18: Ko-fi/BuyMeACoffee one-time spenders
A19: Cost — Phase 1 (paid per accepted piece)
A20: Contributors (paid per piece) | B20: 4 | C20: Phase 1: 3–5, not 10
A21: Rate per big piece (USD) | B21: 30 | C21: accepted big story
A22: Big pieces/mo (contributor-sourced) | B22: 8
A23: Rate per short/small (USD) | B23: 8 | C23: accepted short/small
A24: Shorts/small pieces/mo (contributor) | B24: 30
A25: Tools + production (USD/mo) | B25: 50 | C25: CapCut/hosting/design
A26: Platform infra (USD/mo) | B26: 16.25 | C26: from v0.1

Sheet Revenue to $600
A1: Round 1 — the revenue stack to ~$600/mo
A2: Membership backbone + YT + display + tips. Edit members on Assumptions.
A4: Stream | B4: USD/mo | C4: Note
A5: Membership (members × $5) | B5: =Assumptions!B8*Assumptions!B6 -> 400 | C5: the backbone — diaspora supporters
A6: YouTube long-form ad rev | B6: =Assumptions!B11/1000*Assumptions!B12 -> 120 | C6: diaspora RPM; compounds with subs
A7: Shorts ad rev | B7: =Assumptions!B13/1000*Assumptions!B14 -> 30 | C7: tiny — acquisition, not revenue
A8: Display (site, diaspora) | B8: =Assumptions!B16/1000*Assumptions!B17 -> 211.2 | C8: one clean ad
A9: Tips / donations | B9: =Assumptions!B18 -> 35 | C9: one-time spenders
A10: TOTAL revenue (USD/mo) | B10: =SUM(B5:B9) -> 796.2
A11: vs target | B11: =B10-Assumptions!B4 -> 196.2
A13: Members alone to hit $600 @ $5 / @ $10 | B13: =ROUNDUP(Assumptions!B4/Assumptions!B6,0) -> 120 | C13: =ROUNDUP(Assumptions!B4/Assumptions!B7,0)&" @ $10" -> 60 @ $10
A14: Members implied by conversion × site pv | B14: =Assumptions!B16*Assumptions!B9 -> 600
A15: Reading: 120 members @ $5 = $600 alone. The stack hits it with only ~80 members + modest YT/display/tips.

Sheet Diaspora YT-Shorts
A1: Diaspora YouTube & Shorts economics (by viewer location)
A2: YouTube pays on WHERE viewers are. English content to US/UK diaspora = Tier-1 RPM. Shorts pay tiny.
A4: Monthly views | B4: Long-form $ (@ $4) | C4: Shorts $ (@ $0.10) | D4: Note
A5: 30000 | B5: =A5/1000*Assumptions!$B$12 -> 120 | C5: =A5/1000*Assumptions!$B$14 -> 3 | D5: long-form = revenue; shorts = reach
A6: 100000 | B6: =A6/1000*Assumptions!$B$12 -> 400 | C6: =A6/1000*Assumptions!$B$14 -> 10
A7: 300000 | B7: =A7/1000*Assumptions!$B$12 -> 1200 | C7: =A7/1000*Assumptions!$B$14 -> 30
A8: 1000000 | B8: =A8/1000*Assumptions!$B$12 -> 4000 | C8: =A8/1000*Assumptions!$B$14 -> 100
A10: Takeaway: 300k long-form diaspora views ≈ $1,200/mo; 300k Shorts views ≈ $30. Long-form + membership pays; Shorts acquire.

Sheet Cost & Scaling
A1: Round 2 — cost & scaling
A2: Phase-1 cost (paid per accepted piece) then unit economics at 4 / 10 / 50 contributors.
A4: Phase-1 monthly cost
A5: Big pieces (n × rate) | B5: =Assumptions!B22*Assumptions!B21 -> 240
A6: Shorts/small (n × rate) | B6: =Assumptions!B24*Assumptions!B23 -> 240
A7: Tools + production | B7: =Assumptions!B25 -> 50
A8: Infra | B8: =Assumptions!B26 -> 16.25
A9: Phase-1 total cost (USD/mo) | B9: =SUM(B5:B8) -> 546.25
A11: Phase-1 net (revenue − cost) | B11: ='Revenue to $600'!B10-B9 -> 249.95
A13: Scaling unit economics
A14: Contributors | B14: 4 | C14: 10 | D14: 50
A15: Pieces/mo (scales with contributors) | B15: =(Assumptions!$B$22+Assumptions!$B$24)/Assumptions!$B$20*4 -> 38 | C15: =(Assumptions!$B$22+Assumptions!$B$24)/Assumptions!$B$20*10 -> 95 | D15: =(Assumptions!$B$22+Assumptions!$B$24)/Assumptions!$B$20*50 -> 475
A16: Content cost (USD/mo) | B16: =(Assumptions!$B$22*Assumptions!$B$21+Assumptions!$B$24*Assumptions!$B$23)/Assumptions!$B$20*4 -> 480 | C16: =(Assumptions!$B$22*Assumptions!$B$21+Assumptions!$B$24*Assumptions!$B$23)/Assumptions!$B$20*10 -> 1200 | D16: =(Assumptions!$B$22*Assumptions!$B$21+Assumptions!$B$24*Assumptions!$B$23)/Assumptions!$B$20*50 -> 6000
A17: + central overhead (USD/mo) | B17: 400 | C17: 800 | D17: 2500
A18: Total cost (USD/mo) | B18: =B16+B17 -> 880 | C18: =C16+C17 -> 2000 | D18: =D16+D17 -> 8500
A19: Members to cover (all-membership @ $5) | B19: =ROUNDUP(B18/Assumptions!$B$6,0) -> 176 | C19: =ROUNDUP(C18/Assumptions!$B$6,0) -> 400 | D19: =ROUNDUP(D18/Assumptions!$B$6,0) -> 1700
A21: Note: per-piece pay = variable cost (no idle salary). Overhead/contributor falls with scale. Verification capacity is the real ceiling.

Sheet Sources
A1: Sources
A3: Claim | B3: Source
A4: South Asian diaspora ~44M (India 18M, BD 7.4M, PK 6.3M; UAE 6.2M, US 6.1M, UK 4M, CA 3M) | B4: findeasy.in / Wikipedia South Asian diaspora (UN 2020–22)
A5: YouTube pays by viewer location; English diaspora ~$8 RPM vs India $0.70 | B5: ytmoneycalculator / lenostube / fluxnote 2026
A6: Shorts RPM tiny (~$0.05–0.15) | B6: fluxnote YouTube Shorts RPM 2026
A7: Ada Derana ~3.8M subs / 176k videos; Hiru ~5.1M / 59k | B7: speakrj / Social Blade 2026 (aggregator est.)
A8: Display diaspora clean-ad RPM ~$1.76 | B8: Business Proposition v0.2
A9: Tier-1 salary ~tax-free (LKR 1.8M relief) | B9: Business Proposition v0.3 / SL APIT 2026
