Workbook

Sheet Verdict
A1: The Analyst — Business Proposition v0.3 · Net economics, one-ad path, combined breakeven
A2: Finance: Hasib #30 (lead), Harini #45 · Legal flag: Vinita #47 · Priya #9 · 2026-06-19 · prudent
A4: TAX/FOREX — net to the analyst (NOT tax advice; Vinita/Hasib to verify with IRD)
A5: • SL personal relief = LKR 1.8M/yr = 150k/mo ⇒ a Tier-1 (150k) salary is essentially APIT-tax-free.
A6: • Higher tiers taxed progressively 6–36%: Tier-2 (300k) nets ~282k; Tier-3 (500k) nets ~414k.
A7: • A 15% tax on FOREIGN/forex service income (AdSense, diaspora) may apply if remitted to a SL bank — model both.
A8: • Revenue needed to PAY the gross salary (after ~2% forex spread + $16 infra): T1 ~$518/mo, T2 ~$1,020, T3 ~$1,689.
A10: CAN WE "WIN" WITH ONE CLEAN AD ALONE?
A11: • Programmatic: Tier-1 needs ~440k–600k pageviews/mo; Tier-2 ~0.9–1.2M; Tier-3 ~1.4–1.9M. (Year 2–3+ territory.)
A12: • Direct-sold sole slot: ONE aligned sponsor at ~$520/mo "wins" Tier-1 sooner — but is a single patron (independence risk).
A13: • Verdict: one ad can win Tier-1 ONLY at scale (programmatic) or via a concentrated sponsor (patron). Not at Y1 traffic, programmatically.
A15: COMBINED IS HOW YOU BREAK EVEN (the realistic path)
... A23: Sheets: Assumptions · Net to Analyst · Win with One Ad · Direct Sponsor · Combined Breakeven · Scaling · Sources.

Sheet Assumptions
A1: Assumptions — edit BLUE; verify YELLOW. Prudent. Tax = illustrative, verify with IRD/Vinita.
A3: Salary tiers — GROSS monthly LKR (founder-stated)
A4: Tier-1 gross (LKR/mo) | B4: 150000 | C4: ≈ $500. At personal relief ⇒ ~0 APIT.
A5: Tier-2 gross (LKR/mo) | B5: 300000 | C5: ≈ $1,000.
A6: Tier-3 gross (LKR/mo) | B6: 500000 | C6: ≈ $1,500.
A7: FX / tax / cost
A8: USD→LKR | B8: 305 | C8: verify live rate
A9: Forex + remittance spread | B9: 0.02 | C9: USD revenue → LKR bank conversion + fees
A10: Platform infra (USD/mo) | B10: 16.25 | C10: Business Model v0.1
A11: APIT personal relief (LKR/yr) | B11: 1800000 | C11: 2025/26: first 1.8M tax-free. Source: SL APIT 2026.
A12: Foreign/forex income tax (flat) | B12: 0.15 | C12: 15% on forex service income if remitted (EconomyNext/Sunday Times 2026). VERIFY applicability.
A13: Ad / sponsor / membership
A14: Blended eff. RPM — base mix (USD/1000) | B14: 0.87 | C14: from v0.2 (60/40 SL/diaspora, after fill+adblock)
A15: Blended eff. RPM — diaspora mix (USD/1000) | B15: 1.17 | C15: from v0.2 (40/60)
A16: Direct sole-slot premium (×programmatic) | B16: 2.5 | C16: sole, brand-safe, no auction → premium over programmatic
A17: Direct slot sell-through | B17: 0.7 | C17: % of months the sole slot is actually sold
A18: Membership (USD/member/mo) | B18: 3 | C18: blended; diaspora pays more (model later)
A19: Visitor→member conversion | B19: 0.01 | C19: prudent 0.5–2% of monthly uniques

Sheet Net to Analyst
A1: Round F4 — net to analyst (tax + forex) & revenue needed
A2: APIT computed on salary as sole income (illustrative). Forex tax shown as alternative. Verify with IRD/Vinita.
A4: Line | B4: Tier-1 | C4: Tier-2 | D4: Tier-3
A5: Gross salary (LKR/mo) | B5: =Assumptions!$B$4 -> 150000 | C5: =Assumptions!$B$5 -> 300000 | D5: =Assumptions!$B$6 -> 500000
A6: Gross salary (LKR/yr) | B6: =B5*12 -> 1800000 | C6: =C5*12 -> 3600000 | D6: =D5*12 -> 6000000
A7: APIT income tax (LKR/yr) | B7: =MIN(MAX(0,B6-Assumptions!$B$11),1000000)*0.06+MIN(MAX(MAX(0,B6-Assumptions!$B$11)-1000000,0),500000)*0.18+MIN(MAX(MAX(0,B6-Assumptions!$B$11)-1500000,0),500000)*0.24+MIN(MAX(MAX(0,B6-Assumptions!$B$11)-2000000,0),500000)*0.3+MAX(MAX(0,B6-Assumptions!$B$11)-2500000,0)*0.36 -> 0 | C7: =MIN(MAX(0,C6-Assumptions!$B$11),1000000)*0.06+MIN(MAX(MAX(0,C6-Assumptions!$B$11)-1000000,0),500000)*0.18+MIN(MAX(MAX(0,C6-Assumptions!$B$11)-1500000,0),500000)*0.24+MIN(MAX(MAX(0,C6-Assumptions!$B$11)-2000000,0),500000)*0.3+MAX(MAX(0,C6-Assumptions!$B$11)-2500000,0)*0.36 -> 222000 | D7: =MIN(MAX(0,D6-Assumptions!$B$11),1000000)*0.06+MIN(MAX(MAX(0,D6-Assumptions!$B$11)-1000000,0),500000)*0.18+MIN(MAX(MAX(0,D6-Assumptions!$B$11)-1500000,0),500000)*0.24+MIN(MAX(MAX(0,D6-Assumptions!$B$11)-2000000,0),500000)*0.3+MAX(MAX(0,D6-Assumptions!$B$11)-2500000,0)*0.36 -> 1032000
A8: APIT tax (LKR/mo) | B8: =B7/12 -> 0 | C8: =C7/12 -> 18500 | D8: =D7/12 -> 86000
A9: Net take-home (LKR/mo, APIT) | B9: =B5-B8 -> 150000 | C9: =C5-C8 -> 281500 | D9: =D5-D8 -> 414000
A10: Effective tax rate (APIT) | B10: =B8/B5 -> 0 | C10: =C8/C5 -> 0.061666667 | D10: =D8/D5 -> 0.172
A12: Revenue needed to pay gross (USD/mo) | B12: =B5/Assumptions!$B$8/(1-Assumptions!$B$9)+Assumptions!$B$10 -> 518.09008 | C12: =C5/Assumptions!$B$8/(1-Assumptions!$B$9)+Assumptions!$B$10 -> 1019.9302 | D12: =D5/Assumptions!$B$8/(1-Assumptions!$B$9)+Assumptions!$B$10 -> 1689.0503
A13: If 15% forex tax applies: rev needed (USD/mo) | B13: =B12/(1-Assumptions!$B$12) -> 609.51774 | C13: =C12/(1-Assumptions!$B$12) -> 1199.9178 | D13: =D12/(1-Assumptions!$B$12) -> 1987.118
A15: Note: Tier-1 sits at personal relief ⇒ ~0 APIT. The 15% forex line is the conservative case if AdSense/diaspora income is taxed as forex service income.

Sheet Win with One Ad
A1: Round F5 — can ONE clean ad win a tier alone?
A2: Programmatic pageviews needed, and the direct sole-sponsor monthly rate needed, to cover each tier alone.
A4: Line | B4: Tier-1 | C4: Tier-2 | D4: Tier-3
A5: Revenue needed (USD/mo) | B5: ='Net to Analyst'!B12 -> 518.09008 | C5: ='Net to Analyst'!C12 -> 1019.9302 | D5: ='Net to Analyst'!D12 -> 1689.0503
A6: Programmatic pageviews needed (base RPM $0.87) | B6: ='Net to Analyst'!B12/Assumptions!$B$14*1000 -> 595505.84 | C6: ='Net to Analyst'!C12/Assumptions!$B$14*1000 -> 1172333.5 | D6: ='Net to Analyst'!D12/Assumptions!$B$14*1000 -> 1941437.1
A7: Programmatic pageviews needed (diaspora RPM $1.17) | B7: ='Net to Analyst'!B12/Assumptions!$B$15*1000 -> 442812.03 | C7: ='Net to Analyst'!C12/Assumptions!$B$15*1000 -> 871735.18 | D7: ='Net to Analyst'!D12/Assumptions!$B$15*1000 -> 1443632.7
A8: Direct sole-sponsor needed (flat USD/mo) | B8: ='Net to Analyst'!B12 -> 518.09008 | C8: ='Net to Analyst'!C12 -> 1019.9302 | D8: ='Net to Analyst'!D12 -> 1689.0503
A9: # sponsors at $300/slot to cover tier | B9: =ROUNDUP('Net to Analyst'!B12/300,0) -> 2 | C9: =ROUNDUP('Net to Analyst'!C12/300,0) -> 4 | D9: =ROUNDUP('Net to Analyst'!D12/300,0) -> 6
A11: Verdict: programmatic ad-alone = Year 2–3 scale (440k–1.9M pv). Direct sole-sponsor can win Tier-1 sooner = patron concentration risk.

Sheet Direct Sponsor
A1: Round F6 — direct-sold sole-slot pipeline (market-derived value)
A2: Sole-slot monthly value = pageviews × (blended programmatic RPM × premium) × sell-through. Plus negotiated flat option.
A4: Pageviews/mo | B4: Slot value $/mo (base) | C4: Slot value $/mo (diaspora) | D4: vs Tier-1 ($518)
A5: 40000 | B5: =$A5/1000*Assumptions!$B$14*Assumptions!$B$16*Assumptions!$B$17 -> 60.9 | C5: =$A5/1000*Assumptions!$B$15*Assumptions!$B$16*Assumptions!$B$17 -> 81.9 | D5: =IF(C5>='Net to Analyst'!B12,"covers Tier-1","partial") -> partial
A6: 120000 | B6: =$A6/1000*Assumptions!$B$14*Assumptions!$B$16*Assumptions!$B$17 -> 182.7 | C6: =$A6/1000*Assumptions!$B$15*Assumptions!$B$16*Assumptions!$B$17 -> 245.7 | D6: =IF(C6>='Net to Analyst'!B12,"covers Tier-1","partial") -> partial
A7: 250000 | B7: =$A7/1000*Assumptions!$B$14*Assumptions!$B$16*Assumptions!$B$17 -> 380.625 | C7: =$A7/1000*Assumptions!$B$15*Assumptions!$B$16*Assumptions!$B$17 -> 511.875 | D7: =IF(C7>='Net to Analyst'!B12,"covers Tier-1","partial") -> partial
A8: 500000 | B8: =$A8/1000*Assumptions!$B$14*Assumptions!$B$16*Assumptions!$B$17 -> 761.25 | C8: =$A8/1000*Assumptions!$B$15*Assumptions!$B$16*Assumptions!$B$17 -> 1023.75 | D8: =IF(C8>='Net to Analyst'!B12,"covers Tier-1","partial") -> covers Tier-1
A10: Independence guardrails (Philosophy Forum): cap ≤20% revenue if combined w/ members; sector-screen (no politics/betting/finance/contractors); disclose advertiser; editorial firewall; commons-first (offer to own coops).
A12: Reading: at low Y1 traffic the sole slot is worth ~$100–300/mo market-derived; a negotiated flat deal can exceed that but concentrates the patron.

Sheet Combined Breakeven
A1: Round F7 — combined breakeven (one slot + membership)
A2: ONE ad slot (direct OR programmatic) + membership. Shows members needed to hit Tier-1 at three traffic levels.
A4: Line | B4: 40k pv (Lean) | C4: 120k pv (Base) | D4: 250k pv (Growth)
A5: Monthly pageviews | B5: 40000 | C5: 120000 | D5: 250000
A6: Slot revenue (direct sole-slot) | B6: =B5/1000*Assumptions!$B$14*Assumptions!$B$16*Assumptions!$B$17 -> 60.9 | C6: =C5/1000*Assumptions!$B$14*Assumptions!$B$16*Assumptions!$B$17 -> 182.7 | D6: =D5/1000*Assumptions!$B$14*Assumptions!$B$16*Assumptions!$B$17 -> 380.625
A7: Tier-1 revenue needed (USD/mo) | B7: ='Net to Analyst'!B12 -> 518.09008 | C7: ='Net to Analyst'!B12 -> 518.09008 | D7: ='Net to Analyst'!B12 -> 518.09008
A8: Members needed (after slot) | B8: =MAX(0,ROUNDUP((B7-B6)/Assumptions!$B$18,0)) -> 153 | C8: =MAX(0,ROUNDUP((C7-C6)/Assumptions!$B$18,0)) -> 112 | D8: =MAX(0,ROUNDUP((D7-D6)/Assumptions!$B$18,0)) -> 46
A9: Conversion implied (members ÷ pv) | B9: =B8/B5 -> 0.003825 | C9: =C8/C5 -> 0.00093333333 | D9: =D8/D5 -> 0.000184
A11: Reading: Base (120k pv): sole slot ~$183 + ~112 members ⇒ Tier-1. ~0.09% of pv as members is very achievable.
A12: Lean (40k pv): slot ~$61 + ~153 members. Growth (250k pv): slot ~$381 + ~46 members.

Sheet Scaling
A1: Round F8 — scaling to a stable of branded analysts
A2: Each analyst funds ~own Tier-1 revenue + a share of central overhead (legal/verification/SEO). Illustrative.
A4: Line | B4: 1 analyst | C4: 3 analysts | D4: 6 analysts
A5: Central overhead (USD/mo, shared) | B5: 400 | C5: verification spine ops, legal, SEO/distribution, infra — flat-ish, amortised
A6: Analysts | B6: 1 | C6: 3 | D6: 6
A7: Tier-1 revenue per analyst (USD/mo) | B7: ='Net to Analyst'!B12 -> 518.09008 | C7: ='Net to Analyst'!B12 -> 518.09008 | D7: ='Net to Analyst'!B12 -> 518.09008
A8: Total analyst revenue (USD/mo) | B8: =B6*B7 -> 518.09008 | C8: =C6*C7 -> 1554.2702 | D8: =D6*D7 -> 3108.5405
A9: + central overhead (USD/mo) | B9: =$B$5 -> 400 | C9: =$B$5 -> 400 | D9: =$B$5 -> 400
A10: Total revenue needed (USD/mo) | B10: =B8+$B$5 -> 918.09008 | C10: =C8+$B$5 -> 1954.2702 | D10: =D8+$B$5 -> 3508.5405
A11: Overhead per analyst (USD/mo) | B11: =$B$5/B6 -> 400 | C11: =$B$5/C6 -> 133.33333 | D11: =$B$5/D6 -> 66.666667
A12: Members needed (all-membership, $3) | B12: =ROUNDUP(B10/Assumptions!$B$18,0) -> 307 | C12: =ROUNDUP(C10/Assumptions!$B$18,0) -> 652 | D12: =ROUNDUP(D10/Assumptions!$B$18,0) -> 1170
A14: Marginal economics: overhead/analyst falls as the stable grows (shared services amortise). Binding constraint = verification/legal capacity, not writer count (Mara/Tech Review).

Sheet Sources
A1: Sources (cite before numbers leave council — SD-COMMS-COMPLIANCE-2)
A3: Claim | B3: Source
A4: Salary tiers 150k/300k/500k (gross LKR) | B4: Founder-stated [V:FOUNDER]
A5: APIT 2025/26: relief LKR 1.8M; bands 6–36% | B5: SL APIT 2026 (countrytaxcalc / checkbill / lankatax)
A6: 15% tax on foreign/forex service income | B6: EconomyNext; Sunday Times 2026; taxadvisor.lk (VERIFY applicability w/ Vinita/IRD)
A7: Ad effective RPM (SL $0.29 / diaspora $1.76; blended $0.87–1.17) | B7: Business Proposition v0.2 (AdSense/EthicalAds/viewability 2026)
A8: Direct sole-slot premium over programmatic | B8: Industry norm (brand-safe sole placement); modelled 2.5x — confirm with offers
A9: The Examiner subscription-only comparable | B9: ijnet.org; examiner.media
A10: FX USD→LKR ~305 | B10: ASSUMPTION — verify live
