Workbook

Sheet Verdict
A1: The Analyst — Business Proposition v0.2 · Clean Ad Economics
A2: Yan Finance Review: Hasib #30 (lead), Harini #45, Priya #9 · Mara #14 gaps · 2026-06-19 · prudent basis
A4: SCOPE (reassessed per founder)
A5: • "One ad" = ONE ad unit per page/screen (minimal clean load), not one ad total. • NO paywall, ever.
A6: • Ads = a revenue stream we WILL want, but NOT a central dependency. This round isolates clean ad economics.
A7: • Output target (with Yan agentic/institutional support): ~2 huge + 15–20 big + 20 small (ML-drafted, human-curated)/mo.
A9: CLEAN AD ECONOMICS — the prudent truth
A10: One clean banner, after fill + ad-block, earns an effective RPM of ~$0.29 (Sri Lanka) to ~$1.76 (diaspora).
A11: Programmatic ad-only reaches the Tier-1 salary ($500 → $594 grossed) at roughly 500k–1M pageviews/month.
A12: A new SL investigative brand does not have that in year one. So ADS ALONE ≠ a salary, at any realistic Y1 traffic.
A14: WHERE ADS ACTUALLY PAY
A15: • As a SUPPLEMENT on top of membership: at 120k pv/mo the clean ad adds ~$80–150/mo — real, but ~15–25% of Tier-1.
... A31: Sheets: Assumptions · Ad Unit Economics · Traffic→Revenue · Scenarios · Stress Tests · Output→Traffic · Comparable · Sources.

Sheet Assumptions
A1: Assumptions — edit BLUE; verify YELLOW. Prudent/conservative basis.
A3: Salary tiers (founder-stated, [V:FOUNDER]) & costs
A4: Tier-1 salary (USD/mo) | B4: 500 | C4: LKR 150,000 ≈ $500
A5: Tier-2 salary (USD/mo) | B5: 1000 | C5: LKR 300,000 ≈ $1,000
A6: Tier-3 salary (USD/mo) | B6: 1500 | C6: LKR 500,000 ≈ $1,500
A7: USD→LKR | B7: 305 | C7: verify live rate
A8: Platform infra (USD/mo) | B8: 16.25 | C8: Business Model v0.1
A9: Gross-up (fees/forex/fill loss) | B9: 0.15 | C9: applied to salary+infra for revenue target
A10: Tier-1 gross revenue target (USD/mo) | B10: =(B4+B8)*(1+B9) -> 593.6875
A12: Clean ad unit (ONE banner/page) — gross CPM (USD/1000 impressions)
A13: Sri Lanka CPM | B13: 0.4 | C13: SL=AdSense T9 (lowest). Single banner. Range $0.30–0.80. Source: AdSense/SL CPM 2026.
A14: Diaspora (Tier-1) CPM | B14: 3 | C14: Single clean banner, news. Std banner $1.50–4.00. EthicalAds $2.50 EU/NA. Range $2–6.
A15: Fill rate | B15: 0.9 | C15: % impressions monetised. AdSense high; programmatic ~85–95%.
A16: Ad-block rate — SL | B16: 0.2 | C16: general SL audience
A17: Ad-block rate — diaspora | B17: 0.35 | C17: engaged 18–34 tech cohort blocks heavily (Mara/SQ Mag)
A18: Effective RPM — SL (USD/1000 pv) | B18: =B13*B15*(1-B16) -> 0.288
A19: Effective RPM — diaspora (USD/1000 pv) | B19: =B14*B15*(1-B17) -> 1.755
A21: Alternative & on-ethos levers
A22: Direct-sold single slot (flat USD/mo) | B22: 300 | C22: one aligned sponsor for the sole slot. Patron risk: cap+screen+disclose.
A23: Membership (USD/member/mo) | B23: 3 | C23: blended SL+diaspora; on-ethos primary (Pillar 2)
A24: Assumed recurring members | B24: 150 | C24: editable — drives hybrid total

Sheet Ad Unit Economics
A1: Round F1 — clean ad unit economics (one banner/page)
A2: Effective RPM = CPM × fill × (1 − ad-block). Derived from Assumptions.
A4: Step | B4: Sri Lanka | C4: Diaspora | D4: Note
A5: Gross CPM (USD/1000) | B5: =Assumptions!B13 -> 0.4 | C5: =Assumptions!B14 -> 3 | D5: single clean banner
A6: × Fill rate | B6: =Assumptions!B15 -> 0.9 | C6: =Assumptions!B15 -> 0.9 | D6: monetised impressions
A7: × (1 − ad-block) | B7: =1-Assumptions!B16 -> 0.8 | C7: =1-Assumptions!B17 -> 0.65 | D7: served impressions
A8: Effective RPM (USD/1000 pv) | B8: =Assumptions!B18 -> 0.288 | C8: =Assumptions!B19 -> 1.755 | D8: revenue per 1000 pageviews
A10: Direct-sold alternative
A11: Sell the sole slot to one aligned sponsor, flat/mo | B11: =Assumptions!B22 -> 300 | D11: Can beat programmatic at low traffic; reintroduces patron risk (cap ≤20%, screen sector, disclose).
A13: Reading: at SL ~$0.29 and diaspora ~$1.76 effective RPM, programmatic needs heavy traffic (see Traffic→Revenue).

Sheet Traffic→Revenue
A1: Round F2a — traffic → monthly ad revenue (programmatic, one slot)
A2: Revenue = pageviews × blended effective RPM ÷ 1000. Three blends shown. Tier-1 target marked.
A4: Pageviews / mo | B4: SL-heavy $0.50 | C4: Balanced $1.00 | D4: Diaspora $1.50 | E4: vs Tier-1 ($594)
A5: 50000 | B5: =$A5*0.5/1000 -> 25 | C5: =$A5*1/1000 -> 50 | D5: =$A5*1.5/1000 -> 75 | E5: =IF(C5>=Assumptions!$B$10,"≥ Tier-1 at $1.00","below") -> below
A6: 100000 | B6: =$A6*0.5/1000 -> 50 | C6: =$A6*1/1000 -> 100 | D6: =$A6*1.5/1000 -> 150 | E6: =IF(C6>=Assumptions!$B$10,"≥ Tier-1 at $1.00","below") -> below
A7: 250000 | B7: =$A7*0.5/1000 -> 125 | C7: =$A7*1/1000 -> 250 | D7: =$A7*1.5/1000 -> 375 | E7: =IF(C7>=Assumptions!$B$10,"≥ Tier-1 at $1.00","below") -> below
A8: 500000 | B8: =$A8*0.5/1000 -> 250 | C8: =$A8*1/1000 -> 500 | D8: =$A8*1.5/1000 -> 750 | E8: =IF(C8>=Assumptions!$B$10,"≥ Tier-1 at $1.00","below") -> below
A9: 1000000 | B9: =$A9*0.5/1000 -> 500 | C9: =$A9*1/1000 -> 1000 | D9: =$A9*1.5/1000 -> 1500 | E9: =IF(C9>=Assumptions!$B$10,"≥ Tier-1 at $1.00","below") -> ≥ Tier-1 at $1.00
A11: Blended RPM examples are illustrative; real blend depends on SL/diaspora mix (see Scenarios).
A12: Programmatic ad-only hits Tier-1 (~$594) around 500k pv ($1.00) to 1M pv ($0.50).

Sheet Scenarios
A1: Round F2b — working scenarios (supported-output, ~month 12–24)
A2: Pageviews assume Yan agentic support lifts output (2 huge+~18 big+20 small/mo). Prudent midpoints; lumpy in reality.
A4: Driver | B4: Lean | C4: Base | D4: Growth | E4: Diaspora-tilt
A5: Monthly pageviews | B5: 40000 | C5: 120000 | D5: 300000 | E5: 250000
A6: Sri Lanka traffic share | B6: 0.7 | C6: 0.6 | D6: 0.55 | E6: 0.4
A7: Diaspora share | B7: =1-B6 -> 0.3 | C7: =1-C6 -> 0.4 | D7: =1-D6 -> 0.45 | E7: =1-E6 -> 0.6
A8: Blended effective RPM | B8: =B6*Assumptions!$B$18+(1-B6)*Assumptions!$B$19 -> 0.7281 | C8: =C6*Assumptions!$B$18+(1-C6)*Assumptions!$B$19 -> 0.8748 | D8: =D6*Assumptions!$B$18+(1-D6)*Assumptions!$B$19 -> 0.94815 | E8: =E6*Assumptions!$B$18+(1-E6)*Assumptions!$B$19 -> 1.1682
A9: Ad revenue / mo (programmatic) | B9: =B5/1000*B8 -> 29.124 | C9: =C5/1000*C8 -> 104.976 | D9: =D5/1000*D8 -> 284.445 | E9: =E5/1000*E8 -> 292.05
A10: Membership rev (assumed members) | B10: =Assumptions!$B$24*Assumptions!$B$23 -> 450 | C10: =Assumptions!$B$24*Assumptions!$B$23 -> 450 | D10: =Assumptions!$B$24*Assumptions!$B$23 -> 450 | E10: =Assumptions!$B$24*Assumptions!$B$23 -> 450
A11: Ad + membership total / mo | B11: =B9+B10 -> 479.124 | C11: =C9+C10 -> 554.976 | D11: =D9+D10 -> 734.445 | E11: =E9+E10 -> 742.05
A12: vs Tier-1 target ($594) | B12: =B11-Assumptions!$B$10 -> -114.5635 | C12: =C11-Assumptions!$B$10 -> -38.7115 | D12: =D11-Assumptions!$B$10 -> 140.7575 | E12: =E11-Assumptions!$B$10 -> 148.3625
A13: Pageviews needed: ad-ONLY Tier-1 | B13: =Assumptions!$B$10/B8*1000 -> 815392.8 | C13: =Assumptions!$B$10/C8*1000 -> 678655.12 | D13: =Assumptions!$B$10/D8*1000 -> 626153.56 | E13: =Assumptions!$B$10/E8*1000 -> 508207.07
A14: Ad-only traffic gap (×) | B14: =B13/B5 -> 20.38482 | C14: =C13/C5 -> 5.6554593 | D14: =D13/D5 -> 2.0871785 | E14: =E13/E5 -> 2.0328283
A15: Members for Tier-1 WITH this ad | B15: =MAX(0,ROUNDUP((Assumptions!$B$10-B9)/Assumptions!$B$23,0)) -> 189 | C15: =MAX(0,ROUNDUP((Assumptions!$B$10-C9)/Assumptions!$B$23,0)) -> 163 | D15: =MAX(0,ROUNDUP((Assumptions!$B$10-D9)/Assumptions!$B$23,0)) -> 104 | E15: =MAX(0,ROUNDUP((Assumptions!$B$10-E9)/Assumptions!$B$23,0)) -> 101
A16: Pieces/month (huge+big+small) | B16: 20 | C16: 35 | D16: 40 | E16: 30
A17: Reading: even supported, ad-only is 2–10x short; membership (~130–190 members) + clean ad clears Tier-1.

Sheet Stress Tests
A1: Round F3 — stress tests (Base = 120k pv, balanced; prudent downside)
A2: Each shock applied to the Base scenario ad revenue; shows members still needed for Tier-1.
A4: Shock | B4: Ad rev / mo | C4: Members for Tier-1 | D4: Note
A5: Base case (no shock) | B5: =Scenarios!C9 -> 104.976 | C5: =MAX(0,ROUNDUP((Assumptions!$B$10-B5)/Assumptions!$B$23,0)) -> 163 | D5: reference
A6: Ad-block surge +15pp | B6: =120000/1000*(0.6*Assumptions!B18*(0.75/0.8)+0.4*Assumptions!B19*(0.5/0.65)) -> 84.24 | C6: =MAX(0,ROUNDUP((Assumptions!$B$10-B6)/Assumptions!$B$23,0)) -> 170 | D6: heavier blocking on both segments
A7: CPM crash −30% | B7: =(Scenarios!C9)*0.7 -> 73.4832 | C7: =MAX(0,ROUNDUP((Assumptions!$B$10-B7)/Assumptions!$B$23,0)) -> 174 | D7: programmatic price drop / recession
A8: Diaspora share −15pp (to 45/... ) | B8: =120000/1000*(0.75*Assumptions!B18+0.25*Assumptions!B19) -> 78.57 | C8: =MAX(0,ROUNDUP((Assumptions!$B$10-B8)/Assumptions!$B$23,0)) -> 172 | D8: traffic skews more local
A9: AdSense ban / invalid-traffic (ad=0) | B9: =0 -> 0 | C9: =MAX(0,ROUNDUP((Assumptions!$B$10-B9)/Assumptions!$B$23,0)) -> 198 | D9: single-point failure on political content
A10: LKR devaluation −20% (salary in USD costs more) | B10: =Scenarios!C9 -> 104.976 | C10: =MAX(0,ROUNDUP((Assumptions!$B$10-B10)/Assumptions!$B$23,0)) -> 163 | D10: ad rev USD unchanged; salary target rises — see note
A12: Takeaway: in every downside, membership is the shock absorber. Ad revenue is volatile; member revenue is not.
A13: AdSense-ban row is why ad must never be load-bearing: one policy strike → $0 ad, members unaffected.

Sheet Output→Traffic
A1: Output → traffic (illustrative; ties supported output to pageviews)
A2: Avg pageviews/piece are first-90-day estimates; investigative traffic is power-law (a few pieces dominate).
A4: Content type | B4: Count/mo | C4: Avg pv/piece | D4: Monthly pv | E4: Note
A5: Huge investigations | B5: 2 | C5: 40000 | D5: =B5*C5 -> 80000 | E5: spike + long tail; diaspora-shareable
A6: Big stories | B6: 18 | C6: 5000 | D6: =B6*C6 -> 90000 | E6: beat coverage; SEO + social
A7: Small (ML-drafted, curated) | B7: 20 | C7: 800 | D7: =B7*C7 -> 16000 | E7: long-tail SEO floor; low each, compounds
A8: New-content pv / mo (gross) | D8: =SUM(D5:D7) -> 186000
A10: Note: gross new-content pv overstates steady traffic (overlap, decay). Use Scenarios pv as the prudent monthly figure.

Sheet Comparable
A1: Comparable — The Examiner (Sri Lanka)
A3: Field | B3: Detail
A4: Outlet | B4: The Examiner (examiner.media), Colombo
A5: People | B5: Daniel Alphonsus (CEO/Publisher; ex-Daraz fintech, finance/foreign ministry adviser, Oxford PPE, Harvard) + Mimi Alphonsus (Publisher, ex-Sunday Times)
A6: Model | B6: Subscription-ONLY. "You, dear subscriber, pay our bills." Takes NO advertising. Editorial independence.
A7: Signal | B7: A credible SL outlet chose subscription-only; breakeven is tough (founder note).
A8: Implication for Analyst | B8: Membership is the proven on-ethos lever. Our differentiation: add ONE clean, capped ad they refuse — as supplement, never dependency. No paywall (we stay open; they gate).

Sheet Sources
A1: Sources (SD-COMMS-COMPLIANCE-2: cite before numbers leave council)
A3: Claim | B3: Source
A4: Salary tiers LKR 150k/300k/500k ≈ $500/$1000/$1500 | B4: Founder-stated [V:FOUNDER]
A5: Standard display banner CPM $1.50–4.00; $0.50–$12 by placement | B5: Display advertising statistics 2026 (marketingltb); programmatic stats 2026
A6: SL = AdSense lowest tier (T9); SL Meta CPM ~LKR173 ($0.55) | B6: AdSense RPM-by-country 2026; hypesrilanka 2026; Statista SL
A7: Clean contextual ad ~$2.50 CPM (EU/NA) | B7: EthicalAds publisher guide/prospectus 2026
A8: Viewability ~72% cross-network 2026; desktop banner 64% | B8: amraandelma / comScore / digitalapplied 2026
A9: Fill: vCPM packages +43% price, +28% fill | B9: digitalapplied display benchmarks 2026
A10: Ad-block heaviest in 18–34 tech cohort | B10: SQ Magazine / Backlinko 2026
A11: AdSense ban / invalid-traffic single-point risk | B11: Google AdSense Help
A12: The Examiner subscription-only, no ads | B12: ijnet.org; examiner.media/about
A13: Infra cost basis | B13: Analyst Business Model v0.1
